uberspace_takeout/__init__.py
uberspace_takeout/__main__.py
uberspace_takeout/compat.py
uberspace_takeout/exc.py
uberspace_takeout/storage.py
uberspace_takeout/items/__init__.py
uberspace_takeout/items/base.py
uberspace_takeout/items/common.py
uberspace_takeout/items/u6.py
uberspace_takeout/items/u7.py
uberspace_takeout-0.3.0.dist-info/METADATA
uberspace_takeout-0.3.0.dist-info/WHEEL
uberspace_takeout-0.3.0.dist-info/entry_points.txt
uberspace_takeout-0.3.0.dist-info/top_level.txt
uberspace_takeout-0.3.0.dist-info/zip-safe
uberspace_takeout-0.3.0.dist-info/RECORD
