Metadata-Version: 2.1
Name: uberspace-takeout
Version: 0.3.0
Summary: UNKNOWN
Home-page: https://github.com/uberspace/takeout
Author: uberspace.de
Author-email: hallo@uberspace.de
License: UNKNOWN
Platform: UNKNOWN
Classifier: Development Status :: 5 - Production/Stable
Classifier: Intended Audience :: Developers
Classifier: Intended Audience :: Information Technology
Classifier: Intended Audience :: System Administrators
Classifier: Topic :: System :: Systems Administration
Classifier: Topic :: Security
Classifier: Topic :: Utilities
Classifier: Natural Language :: English
Classifier: Operating System :: POSIX :: Linux
Classifier: Programming Language :: Python :: 2.7
Provides-Extra: test
Requires-Dist: pyfakefs (>=3.6) ; extra == 'test'
Requires-Dist: pytest-mock ; extra == 'test'
